llama_models/__init__.py
llama_models/llama3_1/__init__.py
llama_models/llama3_1/api/__init__.py
llama_models/llama3_1/api/args.py
llama_models/llama3_1/api/chat_format.py
llama_models/llama3_1/api/datatypes.py
llama_models/llama3_1/api/interface.py
llama_models/llama3_1/api/model.py
llama_models/llama3_1/api/sku_list.py
llama_models/llama3_1/api/test_tokenizer.py
llama_models/llama3_1/api/tokenizer.model
llama_models/llama3_1/api/tokenizer.py
llama_models/llama3_1/api/tool_utils.py
llama_models/llama3_1/api/templates/assistant_message.builtin_tool_call.yaml
llama_models/llama3_1/api/templates/assistant_message.custom_tool_call.yaml
llama_models/llama3_1/api/templates/assistant_message.default.yaml
llama_models/llama3_1/api/templates/assistant_message.jinja
llama_models/llama3_1/api/templates/system_message.builtin_and_custom_tools.yaml
llama_models/llama3_1/api/templates/system_message.builtin_tools_only.yaml
llama_models/llama3_1/api/templates/system_message.custom_tools_only.yaml
llama_models/llama3_1/api/templates/system_message.default.yaml
llama_models/llama3_1/api/templates/system_message.jinja
llama_models/llama3_1/api/templates/tool_message.failure.yaml
llama_models/llama3_1/api/templates/tool_message.jinja
llama_models/llama3_1/api/templates/tool_message.success.yaml
llama_models/llama3_1/api/templates/user_message.default.yaml
llama_models/llama3_1/api/templates/user_message.jinja
unique_llama_models-0.0.2.dist-info/METADATA
unique_llama_models-0.0.2.dist-info/WHEEL
unique_llama_models-0.0.2.dist-info/top_level.txt
unique_llama_models-0.0.2.dist-info/RECORD
