Metadata-Version: 2.1
Name: unique-llama-models
Version: 0.0.2
Summary: Llama models
Home-page: https://github.com/meta-llama/llama-models
Author: Meta Llama
Author-email: llama-oss@meta.com
Requires-Python: >=3.10
Requires-Dist: PyYAML
Requires-Dist: blobfile
Requires-Dist: jinja2
Requires-Dist: json-strong-typing
Requires-Dist: torch
Requires-Dist: tiktoken
Requires-Dist: fairscale
Requires-Dist: pydantic ==1.10.13
Requires-Dist: pydantic-core ==2.18.2
